pycronner/__init__.py
pycronner/_cronner.py
pycronner-0.0.1.dist-info/LICENSE
pycronner-0.0.1.dist-info/METADATA
pycronner-0.0.1.dist-info/WHEEL
pycronner-0.0.1.dist-info/top_level.txt
pycronner-0.0.1.dist-info/RECORD
