Metadata-Version: 2.1
Name: pycronner
Version: 0.0.1
Summary: Job scheduling package in python
Home-page: https://github.com/ryangao82/pycronner
Author: Ryan Gao
Author-email: ryan.gao@live.com
License: MIT
Keywords: cron,crontab,schedule,scheduling,scheduler,job scheduling
Platform: UNKNOWN
Classifier: Programming Language :: Python :: 3
Classifier: License :: OSI Approved :: MIT License
Classifier: Operating System :: OS Independent
Requires-Python: >=3.6
License-File: LICENSE
